{
	"backtrace" : 1,
	"backtraceGraph" : 
	{
		"commands" : 
		[
			"ADD_CUSTOM_TARGET",
			"ADD_DEPENDENCIES",
			"MYSQL_ADD_EXECUTABLE",
			"ADD_HARNESS_PLUGIN",
			"_ADD_TEST_FILE",
			"ADD_HARNESS_TEST_FILE",
			"ADD_GOOGLETEST_FILE",
			"add_harness_plugin",
			"ADD_ROUTER_TEST_FILE",
			"add_test_file",
			"ADD_TEST_FILE"
		],
		"files" : 
		[
			"router/CMakeLists.txt",
			"cmake/mysql_add_executable.cmake",
			"router/src/router/src/CMakeLists.txt",
			"router/cmake/Plugin.cmake",
			"router/src/connection_pool/src/CMakeLists.txt",
			"router/src/destination_status/src/CMakeLists.txt",
			"router/src/harness/src/CMakeLists.txt",
			"router/cmake/testing.cmake",
			"router/src/harness/tests/CMakeLists.txt",
			"router/src/harness/tests/plugins/CMakeLists.txt",
			"router/src/http/src/CMakeLists.txt",
			"router/src/http/tests/CMakeLists.txt",
			"router/src/io/src/CMakeLists.txt",
			"router/src/io/tests/CMakeLists.txt",
			"router/src/keepalive/CMakeLists.txt",
			"router/src/keepalive/tests/CMakeLists.txt",
			"router/src/metadata_cache/src/CMakeLists.txt",
			"router/src/metadata_cache/tests/CMakeLists.txt",
			"router/src/mock_server/src/CMakeLists.txt",
			"router/src/mock_server/tests/CMakeLists.txt",
			"router/src/mysql_protocol/tests/CMakeLists.txt",
			"router/src/openssl/src/CMakeLists.txt",
			"router/src/plugin_info/src/CMakeLists.txt",
			"router/src/plugin_info/tests/CMakeLists.txt",
			"router/src/protobuf/src/CMakeLists.txt",
			"router/src/rest_api/src/CMakeLists.txt",
			"router/src/rest_connection_pool/src/CMakeLists.txt",
			"router/src/rest_metadata_cache/src/CMakeLists.txt",
			"router/src/rest_router/src/CMakeLists.txt",
			"router/src/rest_routing/src/CMakeLists.txt",
			"router/src/router/tests/CMakeLists.txt",
			"router/src/routing/src/CMakeLists.txt",
			"router/src/routing/tests/CMakeLists.txt",
			"router/tests/integration/CMakeLists.txt"
		],
		"nodes" : 
		[
			{
				"file" : 0
			},
			{
				"command" : 0,
				"file" : 0,
				"line" : 119,
				"parent" : 0
			},
			{
				"file" : 2
			},
			{
				"command" : 2,
				"file" : 2,
				"line" : 128,
				"parent" : 2
			},
			{
				"command" : 1,
				"file" : 1,
				"line" : 156,
				"parent" : 3
			},
			{
				"command" : 2,
				"file" : 2,
				"line" : 154,
				"parent" : 2
			},
			{
				"command" : 1,
				"file" : 1,
				"line" : 156,
				"parent" : 5
			},
			{
				"file" : 4
			},
			{
				"command" : 3,
				"file" : 4,
				"line" : 69,
				"parent" : 7
			},
			{
				"command" : 1,
				"file" : 3,
				"line" : 93,
				"parent" : 8
			},
			{
				"file" : 5
			},
			{
				"command" : 3,
				"file" : 5,
				"line" : 67,
				"parent" : 10
			},
			{
				"command" : 1,
				"file" : 3,
				"line" : 93,
				"parent" : 11
			},
			{
				"file" : 6
			},
			{
				"command" : 1,
				"file" : 6,
				"line" : 160,
				"parent" : 13
			},
			{
				"command" : 1,
				"file" : 6,
				"line" : 173,
				"parent" : 13
			},
			{
				"command" : 1,
				"file" : 6,
				"line" : 233,
				"parent" : 13
			},
			{
				"command" : 1,
				"file" : 6,
				"line" : 268,
				"parent" : 13
			},
			{
				"file" : 8
			},
			{
				"command" : 5,
				"file" : 8,
				"line" : 85,
				"parent" : 18
			},
			{
				"command" : 4,
				"file" : 7,
				"line" : 68,
				"parent" : 19
			},
			{
				"command" : 1,
				"file" : 7,
				"line" : 124,
				"parent" : 20
			},
			{
				"command" : 5,
				"file" : 8,
				"line" : 85,
				"parent" : 18
			},
			{
				"command" : 4,
				"file" : 7,
				"line" : 68,
				"parent" : 22
			},
			{
				"command" : 1,
				"file" : 7,
				"line" : 124,
				"parent" : 23
			},
			{
				"command" : 5,
				"file" : 8,
				"line" : 85,
				"parent" : 18
			},
			{
				"command" : 4,
				"file" : 7,
				"line" : 68,
				"parent" : 25
			},
			{
				"command" : 1,
				"file" : 7,
				"line" : 124,
				"parent" : 26
			},
			{
				"command" : 5,
				"file" : 8,
				"line" : 85,
				"parent" : 18
			},
			{
				"command" : 4,
				"file" : 7,
				"line" : 68,
				"parent" : 28
			},
			{
				"command" : 1,
				"file" : 7,
				"line" : 124,
				"parent" : 29
			},
			{
				"command" : 5,
				"file" : 8,
				"line" : 85,
				"parent" : 18
			},
			{
				"command" : 4,
				"file" : 7,
				"line" : 68,
				"parent" : 31
			},
			{
				"command" : 1,
				"file" : 7,
				"line" : 124,
				"parent" : 32
			},
			{
				"command" : 5,
				"file" : 8,
				"line" : 85,
				"parent" : 18
			},
			{
				"command" : 4,
				"file" : 7,
				"line" : 68,
				"parent" : 34
			},
			{
				"command" : 1,
				"file" : 7,
				"line" : 124,
				"parent" : 35
			},
			{
				"command" : 5,
				"file" : 8,
				"line" : 85,
				"parent" : 18
			},
			{
				"command" : 4,
				"file" : 7,
				"line" : 68,
				"parent" : 37
			},
			{
				"command" : 1,
				"file" : 7,
				"line" : 124,
				"parent" : 38
			},
			{
				"command" : 5,
				"file" : 8,
				"line" : 85,
				"parent" : 18
			},
			{
				"command" : 4,
				"file" : 7,
				"line" : 68,
				"parent" : 40
			},
			{
				"command" : 1,
				"file" : 7,
				"line" : 124,
				"parent" : 41
			},
			{
				"command" : 5,
				"file" : 8,
				"line" : 85,
				"parent" : 18
			},
			{
				"command" : 4,
				"file" : 7,
				"line" : 68,
				"parent" : 43
			},
			{
				"command" : 1,
				"file" : 7,
				"line" : 124,
				"parent" : 44
			},
			{
				"command" : 5,
				"file" : 8,
				"line" : 85,
				"parent" : 18
			},
			{
				"command" : 4,
				"file" : 7,
				"line" : 68,
				"parent" : 46
			},
			{
				"command" : 1,
				"file" : 7,
				"line" : 124,
				"parent" : 47
			},
			{
				"command" : 5,
				"file" : 8,
				"line" : 85,
				"parent" : 18
			},
			{
				"command" : 4,
				"file" : 7,
				"line" : 68,
				"parent" : 49
			},
			{
				"command" : 1,
				"file" : 7,
				"line" : 124,
				"parent" : 50
			},
			{
				"command" : 5,
				"file" : 8,
				"line" : 85,
				"parent" : 18
			},
			{
				"command" : 4,
				"file" : 7,
				"line" : 68,
				"parent" : 52
			},
			{
				"command" : 1,
				"file" : 7,
				"line" : 124,
				"parent" : 53
			},
			{
				"command" : 5,
				"file" : 8,
				"line" : 85,
				"parent" : 18
			},
			{
				"command" : 4,
				"file" : 7,
				"line" : 68,
				"parent" : 55
			},
			{
				"command" : 1,
				"file" : 7,
				"line" : 124,
				"parent" : 56
			},
			{
				"command" : 5,
				"file" : 8,
				"line" : 85,
				"parent" : 18
			},
			{
				"command" : 4,
				"file" : 7,
				"line" : 68,
				"parent" : 58
			},
			{
				"command" : 1,
				"file" : 7,
				"line" : 124,
				"parent" : 59
			},
			{
				"command" : 5,
				"file" : 8,
				"line" : 85,
				"parent" : 18
			},
			{
				"command" : 4,
				"file" : 7,
				"line" : 68,
				"parent" : 61
			},
			{
				"command" : 1,
				"file" : 7,
				"line" : 124,
				"parent" : 62
			},
			{
				"command" : 5,
				"file" : 8,
				"line" : 85,
				"parent" : 18
			},
			{
				"command" : 4,
				"file" : 7,
				"line" : 68,
				"parent" : 64
			},
			{
				"command" : 1,
				"file" : 7,
				"line" : 124,
				"parent" : 65
			},
			{
				"command" : 5,
				"file" : 8,
				"line" : 85,
				"parent" : 18
			},
			{
				"command" : 4,
				"file" : 7,
				"line" : 68,
				"parent" : 67
			},
			{
				"command" : 1,
				"file" : 7,
				"line" : 124,
				"parent" : 68
			},
			{
				"command" : 5,
				"file" : 8,
				"line" : 85,
				"parent" : 18
			},
			{
				"command" : 4,
				"file" : 7,
				"line" : 68,
				"parent" : 70
			},
			{
				"command" : 1,
				"file" : 7,
				"line" : 124,
				"parent" : 71
			},
			{
				"command" : 5,
				"file" : 8,
				"line" : 85,
				"parent" : 18
			},
			{
				"command" : 4,
				"file" : 7,
				"line" : 68,
				"parent" : 73
			},
			{
				"command" : 1,
				"file" : 7,
				"line" : 124,
				"parent" : 74
			},
			{
				"command" : 5,
				"file" : 8,
				"line" : 85,
				"parent" : 18
			},
			{
				"command" : 4,
				"file" : 7,
				"line" : 68,
				"parent" : 76
			},
			{
				"command" : 1,
				"file" : 7,
				"line" : 124,
				"parent" : 77
			},
			{
				"command" : 5,
				"file" : 8,
				"line" : 85,
				"parent" : 18
			},
			{
				"command" : 4,
				"file" : 7,
				"line" : 68,
				"parent" : 79
			},
			{
				"command" : 1,
				"file" : 7,
				"line" : 124,
				"parent" : 80
			},
			{
				"command" : 5,
				"file" : 8,
				"line" : 85,
				"parent" : 18
			},
			{
				"command" : 4,
				"file" : 7,
				"line" : 68,
				"parent" : 82
			},
			{
				"command" : 1,
				"file" : 7,
				"line" : 124,
				"parent" : 83
			},
			{
				"command" : 5,
				"file" : 8,
				"line" : 85,
				"parent" : 18
			},
			{
				"command" : 4,
				"file" : 7,
				"line" : 68,
				"parent" : 85
			},
			{
				"command" : 1,
				"file" : 7,
				"line" : 124,
				"parent" : 86
			},
			{
				"command" : 5,
				"file" : 8,
				"line" : 85,
				"parent" : 18
			},
			{
				"command" : 4,
				"file" : 7,
				"line" : 68,
				"parent" : 88
			},
			{
				"command" : 1,
				"file" : 7,
				"line" : 124,
				"parent" : 89
			},
			{
				"command" : 5,
				"file" : 8,
				"line" : 85,
				"parent" : 18
			},
			{
				"command" : 4,
				"file" : 7,
				"line" : 68,
				"parent" : 91
			},
			{
				"command" : 1,
				"file" : 7,
				"line" : 124,
				"parent" : 92
			},
			{
				"command" : 5,
				"file" : 8,
				"line" : 85,
				"parent" : 18
			},
			{
				"command" : 4,
				"file" : 7,
				"line" : 68,
				"parent" : 94
			},
			{
				"command" : 1,
				"file" : 7,
				"line" : 124,
				"parent" : 95
			},
			{
				"command" : 5,
				"file" : 8,
				"line" : 110,
				"parent" : 18
			},
			{
				"command" : 4,
				"file" : 7,
				"line" : 68,
				"parent" : 97
			},
			{
				"command" : 1,
				"file" : 7,
				"line" : 124,
				"parent" : 98
			},
			{
				"command" : 5,
				"file" : 8,
				"line" : 110,
				"parent" : 18
			},
			{
				"command" : 4,
				"file" : 7,
				"line" : 68,
				"parent" : 100
			},
			{
				"command" : 1,
				"file" : 7,
				"line" : 124,
				"parent" : 101
			},
			{
				"command" : 5,
				"file" : 8,
				"line" : 120,
				"parent" : 18
			},
			{
				"command" : 4,
				"file" : 7,
				"line" : 68,
				"parent" : 103
			},
			{
				"command" : 1,
				"file" : 7,
				"line" : 124,
				"parent" : 104
			},
			{
				"command" : 6,
				"file" : 8,
				"line" : 148,
				"parent" : 18
			},
			{
				"command" : 4,
				"file" : 7,
				"line" : 82,
				"parent" : 106
			},
			{
				"command" : 1,
				"file" : 7,
				"line" : 124,
				"parent" : 107
			},
			{
				"command" : 6,
				"file" : 8,
				"line" : 148,
				"parent" : 18
			},
			{
				"command" : 4,
				"file" : 7,
				"line" : 82,
				"parent" : 109
			},
			{
				"command" : 1,
				"file" : 7,
				"line" : 124,
				"parent" : 110
			},
			{
				"command" : 6,
				"file" : 8,
				"line" : 148,
				"parent" : 18
			},
			{
				"command" : 4,
				"file" : 7,
				"line" : 82,
				"parent" : 112
			},
			{
				"command" : 1,
				"file" : 7,
				"line" : 124,
				"parent" : 113
			},
			{
				"command" : 6,
				"file" : 8,
				"line" : 148,
				"parent" : 18
			},
			{
				"command" : 4,
				"file" : 7,
				"line" : 82,
				"parent" : 115
			},
			{
				"command" : 1,
				"file" : 7,
				"line" : 124,
				"parent" : 116
			},
			{
				"command" : 6,
				"file" : 8,
				"line" : 148,
				"parent" : 18
			},
			{
				"command" : 4,
				"file" : 7,
				"line" : 82,
				"parent" : 118
			},
			{
				"command" : 1,
				"file" : 7,
				"line" : 124,
				"parent" : 119
			},
			{
				"command" : 6,
				"file" : 8,
				"line" : 148,
				"parent" : 18
			},
			{
				"command" : 4,
				"file" : 7,
				"line" : 82,
				"parent" : 121
			},
			{
				"command" : 1,
				"file" : 7,
				"line" : 124,
				"parent" : 122
			},
			{
				"command" : 6,
				"file" : 8,
				"line" : 148,
				"parent" : 18
			},
			{
				"command" : 4,
				"file" : 7,
				"line" : 82,
				"parent" : 124
			},
			{
				"command" : 1,
				"file" : 7,
				"line" : 124,
				"parent" : 125
			},
			{
				"command" : 6,
				"file" : 8,
				"line" : 148,
				"parent" : 18
			},
			{
				"command" : 4,
				"file" : 7,
				"line" : 82,
				"parent" : 127
			},
			{
				"command" : 1,
				"file" : 7,
				"line" : 124,
				"parent" : 128
			},
			{
				"command" : 6,
				"file" : 8,
				"line" : 148,
				"parent" : 18
			},
			{
				"command" : 4,
				"file" : 7,
				"line" : 82,
				"parent" : 130
			},
			{
				"command" : 1,
				"file" : 7,
				"line" : 124,
				"parent" : 131
			},
			{
				"command" : 6,
				"file" : 8,
				"line" : 148,
				"parent" : 18
			},
			{
				"command" : 4,
				"file" : 7,
				"line" : 82,
				"parent" : 133
			},
			{
				"command" : 1,
				"file" : 7,
				"line" : 124,
				"parent" : 134
			},
			{
				"command" : 6,
				"file" : 8,
				"line" : 148,
				"parent" : 18
			},
			{
				"command" : 4,
				"file" : 7,
				"line" : 82,
				"parent" : 136
			},
			{
				"command" : 1,
				"file" : 7,
				"line" : 124,
				"parent" : 137
			},
			{
				"command" : 6,
				"file" : 8,
				"line" : 148,
				"parent" : 18
			},
			{
				"command" : 4,
				"file" : 7,
				"line" : 82,
				"parent" : 139
			},
			{
				"command" : 1,
				"file" : 7,
				"line" : 124,
				"parent" : 140
			},
			{
				"command" : 6,
				"file" : 8,
				"line" : 148,
				"parent" : 18
			},
			{
				"command" : 4,
				"file" : 7,
				"line" : 82,
				"parent" : 142
			},
			{
				"command" : 1,
				"file" : 7,
				"line" : 124,
				"parent" : 143
			},
			{
				"command" : 6,
				"file" : 8,
				"line" : 148,
				"parent" : 18
			},
			{
				"command" : 4,
				"file" : 7,
				"line" : 82,
				"parent" : 145
			},
			{
				"command" : 1,
				"file" : 7,
				"line" : 124,
				"parent" : 146
			},
			{
				"command" : 6,
				"file" : 8,
				"line" : 148,
				"parent" : 18
			},
			{
				"command" : 4,
				"file" : 7,
				"line" : 82,
				"parent" : 148
			},
			{
				"command" : 1,
				"file" : 7,
				"line" : 124,
				"parent" : 149
			},
			{
				"command" : 6,
				"file" : 8,
				"line" : 148,
				"parent" : 18
			},
			{
				"command" : 4,
				"file" : 7,
				"line" : 82,
				"parent" : 151
			},
			{
				"command" : 1,
				"file" : 7,
				"line" : 124,
				"parent" : 152
			},
			{
				"command" : 6,
				"file" : 8,
				"line" : 148,
				"parent" : 18
			},
			{
				"command" : 4,
				"file" : 7,
				"line" : 82,
				"parent" : 154
			},
			{
				"command" : 1,
				"file" : 7,
				"line" : 124,
				"parent" : 155
			},
			{
				"command" : 6,
				"file" : 8,
				"line" : 152,
				"parent" : 18
			},
			{
				"command" : 4,
				"file" : 7,
				"line" : 82,
				"parent" : 157
			},
			{
				"command" : 1,
				"file" : 7,
				"line" : 124,
				"parent" : 158
			},
			{
				"command" : 6,
				"file" : 8,
				"line" : 170,
				"parent" : 18
			},
			{
				"command" : 4,
				"file" : 7,
				"line" : 82,
				"parent" : 160
			},
			{
				"command" : 1,
				"file" : 7,
				"line" : 124,
				"parent" : 161
			},
			{
				"command" : 6,
				"file" : 8,
				"line" : 170,
				"parent" : 18
			},
			{
				"command" : 4,
				"file" : 7,
				"line" : 82,
				"parent" : 163
			},
			{
				"command" : 1,
				"file" : 7,
				"line" : 124,
				"parent" : 164
			},
			{
				"command" : 6,
				"file" : 8,
				"line" : 170,
				"parent" : 18
			},
			{
				"command" : 4,
				"file" : 7,
				"line" : 82,
				"parent" : 166
			},
			{
				"command" : 1,
				"file" : 7,
				"line" : 124,
				"parent" : 167
			},
			{
				"command" : 6,
				"file" : 8,
				"line" : 170,
				"parent" : 18
			},
			{
				"command" : 4,
				"file" : 7,
				"line" : 82,
				"parent" : 169
			},
			{
				"command" : 1,
				"file" : 7,
				"line" : 124,
				"parent" : 170
			},
			{
				"command" : 6,
				"file" : 8,
				"line" : 170,
				"parent" : 18
			},
			{
				"command" : 4,
				"file" : 7,
				"line" : 82,
				"parent" : 172
			},
			{
				"command" : 1,
				"file" : 7,
				"line" : 124,
				"parent" : 173
			},
			{
				"command" : 6,
				"file" : 8,
				"line" : 170,
				"parent" : 18
			},
			{
				"command" : 4,
				"file" : 7,
				"line" : 82,
				"parent" : 175
			},
			{
				"command" : 1,
				"file" : 7,
				"line" : 124,
				"parent" : 176
			},
			{
				"command" : 6,
				"file" : 8,
				"line" : 170,
				"parent" : 18
			},
			{
				"command" : 4,
				"file" : 7,
				"line" : 82,
				"parent" : 178
			},
			{
				"command" : 1,
				"file" : 7,
				"line" : 124,
				"parent" : 179
			},
			{
				"command" : 1,
				"file" : 8,
				"line" : 191,
				"parent" : 18
			},
			{
				"command" : 1,
				"file" : 8,
				"line" : 195,
				"parent" : 18
			},
			{
				"command" : 1,
				"file" : 8,
				"line" : 199,
				"parent" : 18
			},
			{
				"command" : 1,
				"file" : 8,
				"line" : 203,
				"parent" : 18
			},
			{
				"command" : 1,
				"file" : 8,
				"line" : 207,
				"parent" : 18
			},
			{
				"command" : 1,
				"file" : 8,
				"line" : 211,
				"parent" : 18
			},
			{
				"file" : 9
			},
			{
				"command" : 7,
				"file" : 9,
				"line" : 24,
				"parent" : 187
			},
			{
				"command" : 1,
				"file" : 3,
				"line" : 93,
				"parent" : 188
			},
			{
				"command" : 7,
				"file" : 9,
				"line" : 27,
				"parent" : 187
			},
			{
				"command" : 1,
				"file" : 3,
				"line" : 93,
				"parent" : 190
			},
			{
				"command" : 7,
				"file" : 9,
				"line" : 30,
				"parent" : 187
			},
			{
				"command" : 1,
				"file" : 3,
				"line" : 93,
				"parent" : 192
			},
			{
				"command" : 7,
				"file" : 9,
				"line" : 35,
				"parent" : 187
			},
			{
				"command" : 1,
				"file" : 3,
				"line" : 93,
				"parent" : 194
			},
			{
				"command" : 7,
				"file" : 9,
				"line" : 40,
				"parent" : 187
			},
			{
				"command" : 1,
				"file" : 3,
				"line" : 93,
				"parent" : 196
			},
			{
				"command" : 7,
				"file" : 9,
				"line" : 46,
				"parent" : 187
			},
			{
				"command" : 1,
				"file" : 3,
				"line" : 93,
				"parent" : 198
			},
			{
				"command" : 7,
				"file" : 9,
				"line" : 49,
				"parent" : 187
			},
			{
				"command" : 1,
				"file" : 3,
				"line" : 93,
				"parent" : 200
			},
			{
				"file" : 10
			},
			{
				"command" : 3,
				"file" : 10,
				"line" : 100,
				"parent" : 202
			},
			{
				"command" : 1,
				"file" : 3,
				"line" : 93,
				"parent" : 203
			},
			{
				"command" : 3,
				"file" : 10,
				"line" : 148,
				"parent" : 202
			},
			{
				"command" : 1,
				"file" : 3,
				"line" : 93,
				"parent" : 205
			},
			{
				"command" : 3,
				"file" : 10,
				"line" : 164,
				"parent" : 202
			},
			{
				"command" : 1,
				"file" : 3,
				"line" : 93,
				"parent" : 207
			},
			{
				"command" : 2,
				"file" : 10,
				"line" : 208,
				"parent" : 202
			},
			{
				"command" : 1,
				"file" : 1,
				"line" : 156,
				"parent" : 209
			},
			{
				"command" : 2,
				"file" : 10,
				"line" : 216,
				"parent" : 202
			},
			{
				"command" : 1,
				"file" : 1,
				"line" : 156,
				"parent" : 211
			},
			{
				"file" : 11
			},
			{
				"command" : 9,
				"file" : 11,
				"line" : 27,
				"parent" : 213
			},
			{
				"command" : 8,
				"file" : 7,
				"line" : 39,
				"parent" : 214
			},
			{
				"command" : 4,
				"file" : 7,
				"line" : 53,
				"parent" : 215
			},
			{
				"command" : 1,
				"file" : 7,
				"line" : 124,
				"parent" : 216
			},
			{
				"command" : 9,
				"file" : 11,
				"line" : 32,
				"parent" : 213
			},
			{
				"command" : 8,
				"file" : 7,
				"line" : 39,
				"parent" : 218
			},
			{
				"command" : 4,
				"file" : 7,
				"line" : 53,
				"parent" : 219
			},
			{
				"command" : 1,
				"file" : 7,
				"line" : 124,
				"parent" : 220
			},
			{
				"command" : 9,
				"file" : 11,
				"line" : 37,
				"parent" : 213
			},
			{
				"command" : 8,
				"file" : 7,
				"line" : 39,
				"parent" : 222
			},
			{
				"command" : 4,
				"file" : 7,
				"line" : 53,
				"parent" : 223
			},
			{
				"command" : 1,
				"file" : 7,
				"line" : 124,
				"parent" : 224
			},
			{
				"command" : 9,
				"file" : 11,
				"line" : 42,
				"parent" : 213
			},
			{
				"command" : 8,
				"file" : 7,
				"line" : 39,
				"parent" : 226
			},
			{
				"command" : 4,
				"file" : 7,
				"line" : 53,
				"parent" : 227
			},
			{
				"command" : 1,
				"file" : 7,
				"line" : 124,
				"parent" : 228
			},
			{
				"command" : 9,
				"file" : 11,
				"line" : 46,
				"parent" : 213
			},
			{
				"command" : 8,
				"file" : 7,
				"line" : 39,
				"parent" : 230
			},
			{
				"command" : 4,
				"file" : 7,
				"line" : 53,
				"parent" : 231
			},
			{
				"command" : 1,
				"file" : 7,
				"line" : 124,
				"parent" : 232
			},
			{
				"command" : 9,
				"file" : 11,
				"line" : 50,
				"parent" : 213
			},
			{
				"command" : 8,
				"file" : 7,
				"line" : 39,
				"parent" : 234
			},
			{
				"command" : 4,
				"file" : 7,
				"line" : 53,
				"parent" : 235
			},
			{
				"command" : 1,
				"file" : 7,
				"line" : 124,
				"parent" : 236
			},
			{
				"command" : 9,
				"file" : 11,
				"line" : 54,
				"parent" : 213
			},
			{
				"command" : 8,
				"file" : 7,
				"line" : 39,
				"parent" : 238
			},
			{
				"command" : 4,
				"file" : 7,
				"line" : 53,
				"parent" : 239
			},
			{
				"command" : 1,
				"file" : 7,
				"line" : 124,
				"parent" : 240
			},
			{
				"command" : 9,
				"file" : 11,
				"line" : 59,
				"parent" : 213
			},
			{
				"command" : 8,
				"file" : 7,
				"line" : 39,
				"parent" : 242
			},
			{
				"command" : 4,
				"file" : 7,
				"line" : 53,
				"parent" : 243
			},
			{
				"command" : 1,
				"file" : 7,
				"line" : 124,
				"parent" : 244
			},
			{
				"command" : 9,
				"file" : 11,
				"line" : 71,
				"parent" : 213
			},
			{
				"command" : 8,
				"file" : 7,
				"line" : 39,
				"parent" : 246
			},
			{
				"command" : 4,
				"file" : 7,
				"line" : 53,
				"parent" : 247
			},
			{
				"command" : 1,
				"file" : 7,
				"line" : 124,
				"parent" : 248
			},
			{
				"command" : 9,
				"file" : 11,
				"line" : 81,
				"parent" : 213
			},
			{
				"command" : 8,
				"file" : 7,
				"line" : 39,
				"parent" : 250
			},
			{
				"command" : 4,
				"file" : 7,
				"line" : 53,
				"parent" : 251
			},
			{
				"command" : 1,
				"file" : 7,
				"line" : 124,
				"parent" : 252
			},
			{
				"command" : 9,
				"file" : 11,
				"line" : 90,
				"parent" : 213
			},
			{
				"command" : 8,
				"file" : 7,
				"line" : 39,
				"parent" : 254
			},
			{
				"command" : 4,
				"file" : 7,
				"line" : 53,
				"parent" : 255
			},
			{
				"command" : 1,
				"file" : 7,
				"line" : 124,
				"parent" : 256
			},
			{
				"file" : 12
			},
			{
				"command" : 3,
				"file" : 12,
				"line" : 59,
				"parent" : 258
			},
			{
				"command" : 1,
				"file" : 3,
				"line" : 93,
				"parent" : 259
			},
			{
				"file" : 13
			},
			{
				"command" : 9,
				"file" : 13,
				"line" : 27,
				"parent" : 261
			},
			{
				"command" : 8,
				"file" : 7,
				"line" : 39,
				"parent" : 262
			},
			{
				"command" : 4,
				"file" : 7,
				"line" : 53,
				"parent" : 263
			},
			{
				"command" : 1,
				"file" : 7,
				"line" : 124,
				"parent" : 264
			},
			{
				"command" : 9,
				"file" : 13,
				"line" : 35,
				"parent" : 261
			},
			{
				"command" : 8,
				"file" : 7,
				"line" : 39,
				"parent" : 266
			},
			{
				"command" : 4,
				"file" : 7,
				"line" : 53,
				"parent" : 267
			},
			{
				"command" : 1,
				"file" : 7,
				"line" : 124,
				"parent" : 268
			},
			{
				"file" : 14
			},
			{
				"command" : 7,
				"file" : 14,
				"line" : 24,
				"parent" : 270
			},
			{
				"command" : 1,
				"file" : 3,
				"line" : 93,
				"parent" : 271
			},
			{
				"file" : 15
			},
			{
				"command" : 10,
				"file" : 15,
				"line" : 31,
				"parent" : 273
			},
			{
				"command" : 8,
				"file" : 7,
				"line" : 39,
				"parent" : 274
			},
			{
				"command" : 4,
				"file" : 7,
				"line" : 53,
				"parent" : 275
			},
			{
				"command" : 1,
				"file" : 7,
				"line" : 124,
				"parent" : 276
			},
			{
				"file" : 16
			},
			{
				"command" : 7,
				"file" : 16,
				"line" : 79,
				"parent" : 278
			},
			{
				"command" : 1,
				"file" : 3,
				"line" : 93,
				"parent" : 279
			},
			{
				"file" : 17
			},
			{
				"command" : 10,
				"file" : 17,
				"line" : 40,
				"parent" : 281
			},
			{
				"command" : 8,
				"file" : 7,
				"line" : 39,
				"parent" : 282
			},
			{
				"command" : 4,
				"file" : 7,
				"line" : 53,
				"parent" : 283
			},
			{
				"command" : 1,
				"file" : 7,
				"line" : 124,
				"parent" : 284
			},
			{
				"command" : 10,
				"file" : 17,
				"line" : 40,
				"parent" : 281
			},
			{
				"command" : 8,
				"file" : 7,
				"line" : 39,
				"parent" : 286
			},
			{
				"command" : 4,
				"file" : 7,
				"line" : 53,
				"parent" : 287
			},
			{
				"command" : 1,
				"file" : 7,
				"line" : 124,
				"parent" : 288
			},
			{
				"command" : 10,
				"file" : 17,
				"line" : 55,
				"parent" : 281
			},
			{
				"command" : 8,
				"file" : 7,
				"line" : 39,
				"parent" : 290
			},
			{
				"command" : 4,
				"file" : 7,
				"line" : 53,
				"parent" : 291
			},
			{
				"command" : 1,
				"file" : 7,
				"line" : 124,
				"parent" : 292
			},
			{
				"file" : 18
			},
			{
				"command" : 1,
				"file" : 18,
				"line" : 34,
				"parent" : 294
			},
			{
				"file" : 19
			},
			{
				"command" : 10,
				"file" : 19,
				"line" : 29,
				"parent" : 296
			},
			{
				"command" : 8,
				"file" : 7,
				"line" : 39,
				"parent" : 297
			},
			{
				"command" : 4,
				"file" : 7,
				"line" : 53,
				"parent" : 298
			},
			{
				"command" : 1,
				"file" : 7,
				"line" : 124,
				"parent" : 299
			},
			{
				"file" : 20
			},
			{
				"command" : 6,
				"file" : 20,
				"line" : 34,
				"parent" : 301
			},
			{
				"command" : 4,
				"file" : 7,
				"line" : 82,
				"parent" : 302
			},
			{
				"command" : 1,
				"file" : 7,
				"line" : 124,
				"parent" : 303
			},
			{
				"command" : 6,
				"file" : 20,
				"line" : 34,
				"parent" : 301
			},
			{
				"command" : 4,
				"file" : 7,
				"line" : 82,
				"parent" : 305
			},
			{
				"command" : 1,
				"file" : 7,
				"line" : 124,
				"parent" : 306
			},
			{
				"command" : 6,
				"file" : 20,
				"line" : 34,
				"parent" : 301
			},
			{
				"command" : 4,
				"file" : 7,
				"line" : 82,
				"parent" : 308
			},
			{
				"command" : 1,
				"file" : 7,
				"line" : 124,
				"parent" : 309
			},
			{
				"command" : 6,
				"file" : 20,
				"line" : 34,
				"parent" : 301
			},
			{
				"command" : 4,
				"file" : 7,
				"line" : 82,
				"parent" : 311
			},
			{
				"command" : 1,
				"file" : 7,
				"line" : 124,
				"parent" : 312
			},
			{
				"command" : 6,
				"file" : 20,
				"line" : 34,
				"parent" : 301
			},
			{
				"command" : 4,
				"file" : 7,
				"line" : 82,
				"parent" : 314
			},
			{
				"command" : 1,
				"file" : 7,
				"line" : 124,
				"parent" : 315
			},
			{
				"command" : 6,
				"file" : 20,
				"line" : 34,
				"parent" : 301
			},
			{
				"command" : 4,
				"file" : 7,
				"line" : 82,
				"parent" : 317
			},
			{
				"command" : 1,
				"file" : 7,
				"line" : 124,
				"parent" : 318
			},
			{
				"command" : 6,
				"file" : 20,
				"line" : 50,
				"parent" : 301
			},
			{
				"command" : 4,
				"file" : 7,
				"line" : 82,
				"parent" : 320
			},
			{
				"command" : 1,
				"file" : 7,
				"line" : 124,
				"parent" : 321
			},
			{
				"file" : 21
			},
			{
				"command" : 3,
				"file" : 21,
				"line" : 26,
				"parent" : 323
			},
			{
				"command" : 1,
				"file" : 3,
				"line" : 93,
				"parent" : 324
			},
			{
				"file" : 22
			},
			{
				"command" : 2,
				"file" : 22,
				"line" : 24,
				"parent" : 326
			},
			{
				"command" : 1,
				"file" : 1,
				"line" : 156,
				"parent" : 327
			},
			{
				"file" : 23
			},
			{
				"command" : 9,
				"file" : 23,
				"line" : 52,
				"parent" : 329
			},
			{
				"command" : 8,
				"file" : 7,
				"line" : 39,
				"parent" : 330
			},
			{
				"command" : 4,
				"file" : 7,
				"line" : 53,
				"parent" : 331
			},
			{
				"command" : 1,
				"file" : 7,
				"line" : 124,
				"parent" : 332
			},
			{
				"file" : 24
			},
			{
				"command" : 3,
				"file" : 24,
				"line" : 26,
				"parent" : 334
			},
			{
				"command" : 1,
				"file" : 3,
				"line" : 93,
				"parent" : 335
			},
			{
				"file" : 25
			},
			{
				"command" : 3,
				"file" : 25,
				"line" : 36,
				"parent" : 337
			},
			{
				"command" : 1,
				"file" : 3,
				"line" : 93,
				"parent" : 338
			},
			{
				"file" : 26
			},
			{
				"command" : 3,
				"file" : 26,
				"line" : 26,
				"parent" : 340
			},
			{
				"command" : 1,
				"file" : 3,
				"line" : 93,
				"parent" : 341
			},
			{
				"file" : 27
			},
			{
				"command" : 3,
				"file" : 27,
				"line" : 23,
				"parent" : 343
			},
			{
				"command" : 1,
				"file" : 3,
				"line" : 93,
				"parent" : 344
			},
			{
				"file" : 28
			},
			{
				"command" : 3,
				"file" : 28,
				"line" : 26,
				"parent" : 346
			},
			{
				"command" : 1,
				"file" : 3,
				"line" : 93,
				"parent" : 347
			},
			{
				"file" : 29
			},
			{
				"command" : 3,
				"file" : 29,
				"line" : 26,
				"parent" : 349
			},
			{
				"command" : 1,
				"file" : 3,
				"line" : 93,
				"parent" : 350
			},
			{
				"file" : 30
			},
			{
				"command" : 5,
				"file" : 30,
				"line" : 33,
				"parent" : 352
			},
			{
				"command" : 4,
				"file" : 7,
				"line" : 68,
				"parent" : 353
			},
			{
				"command" : 1,
				"file" : 7,
				"line" : 124,
				"parent" : 354
			},
			{
				"command" : 5,
				"file" : 30,
				"line" : 46,
				"parent" : 352
			},
			{
				"command" : 4,
				"file" : 7,
				"line" : 68,
				"parent" : 356
			},
			{
				"command" : 1,
				"file" : 7,
				"line" : 124,
				"parent" : 357
			},
			{
				"command" : 5,
				"file" : 30,
				"line" : 58,
				"parent" : 352
			},
			{
				"command" : 4,
				"file" : 7,
				"line" : 68,
				"parent" : 359
			},
			{
				"command" : 1,
				"file" : 7,
				"line" : 124,
				"parent" : 360
			},
			{
				"command" : 5,
				"file" : 30,
				"line" : 72,
				"parent" : 352
			},
			{
				"command" : 4,
				"file" : 7,
				"line" : 68,
				"parent" : 362
			},
			{
				"command" : 1,
				"file" : 7,
				"line" : 124,
				"parent" : 363
			},
			{
				"command" : 5,
				"file" : 30,
				"line" : 86,
				"parent" : 352
			},
			{
				"command" : 4,
				"file" : 7,
				"line" : 68,
				"parent" : 365
			},
			{
				"command" : 1,
				"file" : 7,
				"line" : 124,
				"parent" : 366
			},
			{
				"command" : 5,
				"file" : 30,
				"line" : 100,
				"parent" : 352
			},
			{
				"command" : 4,
				"file" : 7,
				"line" : 68,
				"parent" : 368
			},
			{
				"command" : 1,
				"file" : 7,
				"line" : 124,
				"parent" : 369
			},
			{
				"command" : 5,
				"file" : 30,
				"line" : 114,
				"parent" : 352
			},
			{
				"command" : 4,
				"file" : 7,
				"line" : 68,
				"parent" : 371
			},
			{
				"command" : 1,
				"file" : 7,
				"line" : 124,
				"parent" : 372
			},
			{
				"command" : 5,
				"file" : 30,
				"line" : 129,
				"parent" : 352
			},
			{
				"command" : 4,
				"file" : 7,
				"line" : 68,
				"parent" : 374
			},
			{
				"command" : 1,
				"file" : 7,
				"line" : 124,
				"parent" : 375
			},
			{
				"command" : 5,
				"file" : 30,
				"line" : 145,
				"parent" : 352
			},
			{
				"command" : 4,
				"file" : 7,
				"line" : 68,
				"parent" : 377
			},
			{
				"command" : 1,
				"file" : 7,
				"line" : 124,
				"parent" : 378
			},
			{
				"command" : 5,
				"file" : 30,
				"line" : 167,
				"parent" : 352
			},
			{
				"command" : 4,
				"file" : 7,
				"line" : 68,
				"parent" : 380
			},
			{
				"command" : 1,
				"file" : 7,
				"line" : 124,
				"parent" : 381
			},
			{
				"command" : 5,
				"file" : 30,
				"line" : 180,
				"parent" : 352
			},
			{
				"command" : 4,
				"file" : 7,
				"line" : 68,
				"parent" : 383
			},
			{
				"command" : 1,
				"file" : 7,
				"line" : 124,
				"parent" : 384
			},
			{
				"command" : 5,
				"file" : 30,
				"line" : 196,
				"parent" : 352
			},
			{
				"command" : 4,
				"file" : 7,
				"line" : 68,
				"parent" : 386
			},
			{
				"command" : 1,
				"file" : 7,
				"line" : 124,
				"parent" : 387
			},
			{
				"command" : 5,
				"file" : 30,
				"line" : 196,
				"parent" : 352
			},
			{
				"command" : 4,
				"file" : 7,
				"line" : 68,
				"parent" : 389
			},
			{
				"command" : 1,
				"file" : 7,
				"line" : 124,
				"parent" : 390
			},
			{
				"command" : 5,
				"file" : 30,
				"line" : 209,
				"parent" : 352
			},
			{
				"command" : 4,
				"file" : 7,
				"line" : 68,
				"parent" : 392
			},
			{
				"command" : 1,
				"file" : 7,
				"line" : 124,
				"parent" : 393
			},
			{
				"file" : 31
			},
			{
				"command" : 7,
				"file" : 31,
				"line" : 169,
				"parent" : 395
			},
			{
				"command" : 1,
				"file" : 3,
				"line" : 93,
				"parent" : 396
			},
			{
				"file" : 32
			},
			{
				"command" : 10,
				"file" : 32,
				"line" : 56,
				"parent" : 398
			},
			{
				"command" : 8,
				"file" : 7,
				"line" : 39,
				"parent" : 399
			},
			{
				"command" : 4,
				"file" : 7,
				"line" : 53,
				"parent" : 400
			},
			{
				"command" : 1,
				"file" : 7,
				"line" : 124,
				"parent" : 401
			},
			{
				"command" : 10,
				"file" : 32,
				"line" : 56,
				"parent" : 398
			},
			{
				"command" : 8,
				"file" : 7,
				"line" : 39,
				"parent" : 403
			},
			{
				"command" : 4,
				"file" : 7,
				"line" : 53,
				"parent" : 404
			},
			{
				"command" : 1,
				"file" : 7,
				"line" : 124,
				"parent" : 405
			},
			{
				"command" : 10,
				"file" : 32,
				"line" : 56,
				"parent" : 398
			},
			{
				"command" : 8,
				"file" : 7,
				"line" : 39,
				"parent" : 407
			},
			{
				"command" : 4,
				"file" : 7,
				"line" : 53,
				"parent" : 408
			},
			{
				"command" : 1,
				"file" : 7,
				"line" : 124,
				"parent" : 409
			},
			{
				"command" : 10,
				"file" : 32,
				"line" : 56,
				"parent" : 398
			},
			{
				"command" : 8,
				"file" : 7,
				"line" : 39,
				"parent" : 411
			},
			{
				"command" : 4,
				"file" : 7,
				"line" : 53,
				"parent" : 412
			},
			{
				"command" : 1,
				"file" : 7,
				"line" : 124,
				"parent" : 413
			},
			{
				"command" : 10,
				"file" : 32,
				"line" : 56,
				"parent" : 398
			},
			{
				"command" : 8,
				"file" : 7,
				"line" : 39,
				"parent" : 415
			},
			{
				"command" : 4,
				"file" : 7,
				"line" : 53,
				"parent" : 416
			},
			{
				"command" : 1,
				"file" : 7,
				"line" : 124,
				"parent" : 417
			},
			{
				"command" : 10,
				"file" : 32,
				"line" : 56,
				"parent" : 398
			},
			{
				"command" : 8,
				"file" : 7,
				"line" : 39,
				"parent" : 419
			},
			{
				"command" : 4,
				"file" : 7,
				"line" : 53,
				"parent" : 420
			},
			{
				"command" : 1,
				"file" : 7,
				"line" : 124,
				"parent" : 421
			},
			{
				"command" : 10,
				"file" : 32,
				"line" : 56,
				"parent" : 398
			},
			{
				"command" : 8,
				"file" : 7,
				"line" : 39,
				"parent" : 423
			},
			{
				"command" : 4,
				"file" : 7,
				"line" : 53,
				"parent" : 424
			},
			{
				"command" : 1,
				"file" : 7,
				"line" : 124,
				"parent" : 425
			},
			{
				"command" : 10,
				"file" : 32,
				"line" : 56,
				"parent" : 398
			},
			{
				"command" : 8,
				"file" : 7,
				"line" : 39,
				"parent" : 427
			},
			{
				"command" : 4,
				"file" : 7,
				"line" : 53,
				"parent" : 428
			},
			{
				"command" : 1,
				"file" : 7,
				"line" : 124,
				"parent" : 429
			},
			{
				"command" : 10,
				"file" : 32,
				"line" : 56,
				"parent" : 398
			},
			{
				"command" : 8,
				"file" : 7,
				"line" : 39,
				"parent" : 431
			},
			{
				"command" : 4,
				"file" : 7,
				"line" : 53,
				"parent" : 432
			},
			{
				"command" : 1,
				"file" : 7,
				"line" : 124,
				"parent" : 433
			},
			{
				"command" : 10,
				"file" : 32,
				"line" : 56,
				"parent" : 398
			},
			{
				"command" : 8,
				"file" : 7,
				"line" : 39,
				"parent" : 435
			},
			{
				"command" : 4,
				"file" : 7,
				"line" : 53,
				"parent" : 436
			},
			{
				"command" : 1,
				"file" : 7,
				"line" : 124,
				"parent" : 437
			},
			{
				"command" : 10,
				"file" : 32,
				"line" : 56,
				"parent" : 398
			},
			{
				"command" : 8,
				"file" : 7,
				"line" : 39,
				"parent" : 439
			},
			{
				"command" : 4,
				"file" : 7,
				"line" : 53,
				"parent" : 440
			},
			{
				"command" : 1,
				"file" : 7,
				"line" : 124,
				"parent" : 441
			},
			{
				"command" : 10,
				"file" : 32,
				"line" : 56,
				"parent" : 398
			},
			{
				"command" : 8,
				"file" : 7,
				"line" : 39,
				"parent" : 443
			},
			{
				"command" : 4,
				"file" : 7,
				"line" : 53,
				"parent" : 444
			},
			{
				"command" : 1,
				"file" : 7,
				"line" : 124,
				"parent" : 445
			},
			{
				"command" : 10,
				"file" : 32,
				"line" : 68,
				"parent" : 398
			},
			{
				"command" : 8,
				"file" : 7,
				"line" : 39,
				"parent" : 447
			},
			{
				"command" : 4,
				"file" : 7,
				"line" : 53,
				"parent" : 448
			},
			{
				"command" : 1,
				"file" : 7,
				"line" : 124,
				"parent" : 449
			},
			{
				"command" : 8,
				"file" : 32,
				"line" : 93,
				"parent" : 398
			},
			{
				"command" : 4,
				"file" : 7,
				"line" : 53,
				"parent" : 451
			},
			{
				"command" : 1,
				"file" : 7,
				"line" : 124,
				"parent" : 452
			},
			{
				"file" : 33
			},
			{
				"command" : 10,
				"file" : 33,
				"line" : 33,
				"parent" : 454
			},
			{
				"command" : 8,
				"file" : 7,
				"line" : 39,
				"parent" : 455
			},
			{
				"command" : 4,
				"file" : 7,
				"line" : 53,
				"parent" : 456
			},
			{
				"command" : 1,
				"file" : 7,
				"line" : 124,
				"parent" : 457
			},
			{
				"command" : 10,
				"file" : 33,
				"line" : 33,
				"parent" : 454
			},
			{
				"command" : 8,
				"file" : 7,
				"line" : 39,
				"parent" : 459
			},
			{
				"command" : 4,
				"file" : 7,
				"line" : 53,
				"parent" : 460
			},
			{
				"command" : 1,
				"file" : 7,
				"line" : 124,
				"parent" : 461
			},
			{
				"command" : 10,
				"file" : 33,
				"line" : 33,
				"parent" : 454
			},
			{
				"command" : 8,
				"file" : 7,
				"line" : 39,
				"parent" : 463
			},
			{
				"command" : 4,
				"file" : 7,
				"line" : 53,
				"parent" : 464
			},
			{
				"command" : 1,
				"file" : 7,
				"line" : 124,
				"parent" : 465
			},
			{
				"command" : 10,
				"file" : 33,
				"line" : 33,
				"parent" : 454
			},
			{
				"command" : 8,
				"file" : 7,
				"line" : 39,
				"parent" : 467
			},
			{
				"command" : 4,
				"file" : 7,
				"line" : 53,
				"parent" : 468
			},
			{
				"command" : 1,
				"file" : 7,
				"line" : 124,
				"parent" : 469
			},
			{
				"command" : 10,
				"file" : 33,
				"line" : 33,
				"parent" : 454
			},
			{
				"command" : 8,
				"file" : 7,
				"line" : 39,
				"parent" : 471
			},
			{
				"command" : 4,
				"file" : 7,
				"line" : 53,
				"parent" : 472
			},
			{
				"command" : 1,
				"file" : 7,
				"line" : 124,
				"parent" : 473
			}
		]
	},
	"dependencies" : 
	[
		{
			"backtrace" : 4,
			"id" : "mysqlrouter::@6ed13d653485996da371"
		},
		{
			"backtrace" : 6,
			"id" : "mysqlrouter_keyring::@6ed13d653485996da371"
		},
		{
			"backtrace" : 9,
			"id" : "connection_pool_plugin::@2e4889409431ba051e61"
		},
		{
			"backtrace" : 12,
			"id" : "destination_status_plugin::@028a40ec2809c4627ad1"
		},
		{
			"backtrace" : 14,
			"id" : "harness-archive::@27553637d7cd8e81ae3b"
		},
		{
			"backtrace" : 15,
			"id" : "harness-library::@27553637d7cd8e81ae3b"
		},
		{
			"backtrace" : 16,
			"id" : "harness_stdx::@27553637d7cd8e81ae3b"
		},
		{
			"backtrace" : 17,
			"id" : "harness_tls::@27553637d7cd8e81ae3b"
		},
		{
			"backtrace" : 21,
			"id" : "routertest_harness_access_rights::@5432b8fe29535625d31d"
		},
		{
			"backtrace" : 24,
			"id" : "routertest_harness_utility_string::@5432b8fe29535625d31d"
		},
		{
			"backtrace" : 27,
			"id" : "routertest_harness_loader::@5432b8fe29535625d31d"
		},
		{
			"backtrace" : 30,
			"id" : "routertest_harness_loader_lifecycle::@5432b8fe29535625d31d"
		},
		{
			"backtrace" : 33,
			"id" : "routertest_harness_logging::@5432b8fe29535625d31d"
		},
		{
			"backtrace" : 36,
			"id" : "routertest_harness_designator::@5432b8fe29535625d31d"
		},
		{
			"backtrace" : 39,
			"id" : "routertest_harness_iterator::@5432b8fe29535625d31d"
		},
		{
			"backtrace" : 42,
			"id" : "routertest_harness_utilities::@5432b8fe29535625d31d"
		},
		{
			"backtrace" : 45,
			"id" : "routertest_harness_common::@5432b8fe29535625d31d"
		},
		{
			"backtrace" : 48,
			"id" : "routertest_harness_config::@5432b8fe29535625d31d"
		},
		{
			"backtrace" : 51,
			"id" : "routertest_harness_filesystem::@5432b8fe29535625d31d"
		},
		{
			"backtrace" : 54,
			"id" : "routertest_harness_hostname_validator::@5432b8fe29535625d31d"
		},
		{
			"backtrace" : 57,
			"id" : "routertest_harness_bug22104451::@5432b8fe29535625d31d"
		},
		{
			"backtrace" : 60,
			"id" : "routertest_harness_random_generator::@5432b8fe29535625d31d"
		},
		{
			"backtrace" : 63,
			"id" : "routertest_harness_mysql_router_thread::@5432b8fe29535625d31d"
		},
		{
			"backtrace" : 66,
			"id" : "routertest_harness_mpmc_queue::@5432b8fe29535625d31d"
		},
		{
			"backtrace" : 69,
			"id" : "routertest_harness_dynamic_state::@5432b8fe29535625d31d"
		},
		{
			"backtrace" : 72,
			"id" : "routertest_harness_arg_handler::@5432b8fe29535625d31d"
		},
		{
			"backtrace" : 75,
			"id" : "routertest_harness_vt100::@5432b8fe29535625d31d"
		},
		{
			"backtrace" : 78,
			"id" : "routertest_harness_string_utils::@5432b8fe29535625d31d"
		},
		{
			"backtrace" : 81,
			"id" : "routertest_harness_process_launcher::@5432b8fe29535625d31d"
		},
		{
			"backtrace" : 84,
			"id" : "routertest_harness_tcp_address::@5432b8fe29535625d31d"
		},
		{
			"backtrace" : 87,
			"id" : "routertest_harness_config_builder::@5432b8fe29535625d31d"
		},
		{
			"backtrace" : 90,
			"id" : "routertest_harness_event_state_tracker::@5432b8fe29535625d31d"
		},
		{
			"backtrace" : 93,
			"id" : "routertest_harness_config_option::@5432b8fe29535625d31d"
		},
		{
			"backtrace" : 96,
			"id" : "routertest_harness_hexify::@5432b8fe29535625d31d"
		},
		{
			"backtrace" : 99,
			"id" : "routertest_harness_keyring::@5432b8fe29535625d31d"
		},
		{
			"backtrace" : 102,
			"id" : "routertest_harness_keyring_manager::@5432b8fe29535625d31d"
		},
		{
			"backtrace" : 105,
			"id" : "routertest_harness_tls_server_context::@5432b8fe29535625d31d"
		},
		{
			"backtrace" : 108,
			"id" : "routertest_harness_net_ts_buffer::@5432b8fe29535625d31d"
		},
		{
			"backtrace" : 111,
			"id" : "routertest_harness_net_ts_executor::@5432b8fe29535625d31d"
		},
		{
			"backtrace" : 114,
			"id" : "routertest_harness_net_ts_impl_callstack::@5432b8fe29535625d31d"
		},
		{
			"backtrace" : 117,
			"id" : "routertest_harness_net_ts_impl_file::@5432b8fe29535625d31d"
		},
		{
			"backtrace" : 120,
			"id" : "routertest_harness_net_ts_impl_io_service_base::@5432b8fe29535625d31d"
		},
		{
			"backtrace" : 123,
			"id" : "routertest_harness_net_ts_impl_kqueue_io_service::@5432b8fe29535625d31d"
		},
		{
			"backtrace" : 126,
			"id" : "routertest_harness_net_ts_impl_linux_epoll_io_service::@5432b8fe29535625d31d"
		},
		{
			"backtrace" : 129,
			"id" : "routertest_harness_net_ts_impl_netif::@5432b8fe29535625d31d"
		},
		{
			"backtrace" : 132,
			"id" : "routertest_harness_net_ts_impl_poll_io_service::@5432b8fe29535625d31d"
		},
		{
			"backtrace" : 135,
			"id" : "routertest_harness_net_ts_impl_resolver::@5432b8fe29535625d31d"
		},
		{
			"backtrace" : 138,
			"id" : "routertest_harness_net_ts_impl_socket::@5432b8fe29535625d31d"
		},
		{
			"backtrace" : 141,
			"id" : "routertest_harness_net_ts_internet::@5432b8fe29535625d31d"
		},
		{
			"backtrace" : 144,
			"id" : "routertest_harness_net_ts_io_context::@5432b8fe29535625d31d"
		},
		{
			"backtrace" : 147,
			"id" : "routertest_harness_net_ts_io_context_socket::@5432b8fe29535625d31d"
		},
		{
			"backtrace" : 150,
			"id" : "routertest_harness_net_ts_socket::@5432b8fe29535625d31d"
		},
		{
			"backtrace" : 153,
			"id" : "routertest_harness_net_ts_timer::@5432b8fe29535625d31d"
		},
		{
			"backtrace" : 156,
			"id" : "routertest_harness_net_ts_win32_named_pipe::@5432b8fe29535625d31d"
		},
		{
			"backtrace" : 159,
			"id" : "routertest_harness_net_ts_local::@5432b8fe29535625d31d"
		},
		{
			"backtrace" : 162,
			"id" : "routertest_harness_stdx_bit::@5432b8fe29535625d31d"
		},
		{
			"backtrace" : 165,
			"id" : "routertest_harness_stdx_expected::@5432b8fe29535625d31d"
		},
		{
			"backtrace" : 168,
			"id" : "routertest_harness_stdx_flags::@5432b8fe29535625d31d"
		},
		{
			"backtrace" : 171,
			"id" : "routertest_harness_stdx_io_file_handle::@5432b8fe29535625d31d"
		},
		{
			"backtrace" : 174,
			"id" : "routertest_harness_stdx_monitor::@5432b8fe29535625d31d"
		},
		{
			"backtrace" : 177,
			"id" : "routertest_harness_stdx_span::@5432b8fe29535625d31d"
		},
		{
			"backtrace" : 180,
			"id" : "routertest_harness_stdx_ranges::@5432b8fe29535625d31d"
		},
		{
			"backtrace" : 181,
			"id" : "net_ts_netifs::@5432b8fe29535625d31d"
		},
		{
			"backtrace" : 182,
			"id" : "net_ts_connect::@5432b8fe29535625d31d"
		},
		{
			"backtrace" : 183,
			"id" : "net_ts_accept::@5432b8fe29535625d31d"
		},
		{
			"backtrace" : 184,
			"id" : "net_ts_forward::@5432b8fe29535625d31d"
		},
		{
			"backtrace" : 185,
			"id" : "acl_cli::@5432b8fe29535625d31d"
		},
		{
			"backtrace" : 186,
			"id" : "linux_timestamping::@5432b8fe29535625d31d"
		},
		{
			"backtrace" : 189,
			"id" : "routertestplugin_bad_one::@1ae301725c89ed4a2e52"
		},
		{
			"backtrace" : 191,
			"id" : "routertestplugin_bad_two::@1ae301725c89ed4a2e52"
		},
		{
			"backtrace" : 193,
			"id" : "routertestplugin_magic::@1ae301725c89ed4a2e52"
		},
		{
			"backtrace" : 195,
			"id" : "routertestplugin_example::@1ae301725c89ed4a2e52"
		},
		{
			"backtrace" : 197,
			"id" : "routertestplugin_lifecycle::@1ae301725c89ed4a2e52"
		},
		{
			"backtrace" : 199,
			"id" : "routertestplugin_lifecycle2::@1ae301725c89ed4a2e52"
		},
		{
			"backtrace" : 201,
			"id" : "routertestplugin_lifecycle3::@1ae301725c89ed4a2e52"
		},
		{
			"backtrace" : 204,
			"id" : "http_auth_backend::@791fe1f03827c85194f1"
		},
		{
			"backtrace" : 206,
			"id" : "http_auth_realm::@791fe1f03827c85194f1"
		},
		{
			"backtrace" : 208,
			"id" : "http_server::@791fe1f03827c85194f1"
		},
		{
			"backtrace" : 210,
			"id" : "rest_cli::@791fe1f03827c85194f1"
		},
		{
			"backtrace" : 212,
			"id" : "mysqlrouter_passwd::@791fe1f03827c85194f1"
		},
		{
			"backtrace" : 217,
			"id" : "routertest_http_time::@8e2a41002897013f948d"
		},
		{
			"backtrace" : 221,
			"id" : "routertest_http_http_uri::@8e2a41002897013f948d"
		},
		{
			"backtrace" : 225,
			"id" : "routertest_http_base64::@8e2a41002897013f948d"
		},
		{
			"backtrace" : 229,
			"id" : "routertest_http_auth_backend::@8e2a41002897013f948d"
		},
		{
			"backtrace" : 233,
			"id" : "routertest_http_kdf_sha_crypt::@8e2a41002897013f948d"
		},
		{
			"backtrace" : 237,
			"id" : "routertest_http_kdf_pbkdf2::@8e2a41002897013f948d"
		},
		{
			"backtrace" : 241,
			"id" : "routertest_http_passwd::@8e2a41002897013f948d"
		},
		{
			"backtrace" : 245,
			"id" : "routertest_http_auth::@8e2a41002897013f948d"
		},
		{
			"backtrace" : 249,
			"id" : "routertest_http_auth_method::@8e2a41002897013f948d"
		},
		{
			"backtrace" : 253,
			"id" : "routertest_http_content_type::@8e2a41002897013f948d"
		},
		{
			"backtrace" : 257,
			"id" : "routertest_http_matcher::@8e2a41002897013f948d"
		},
		{
			"backtrace" : 260,
			"id" : "io::@47a215310b7df7f2b0d0"
		},
		{
			"backtrace" : 265,
			"id" : "routertest_io_io_plugin::@73b4670b699eb0bc0122"
		},
		{
			"backtrace" : 269,
			"id" : "routertest_io_io_component::@73b4670b699eb0bc0122"
		},
		{
			"backtrace" : 272,
			"id" : "keepalive::@ad5e3fa667e5feea6a37"
		},
		{
			"backtrace" : 277,
			"id" : "routertest_harness_plugin_keepalive::@d43b73986dacf55890ab"
		},
		{
			"backtrace" : 280,
			"id" : "metadata_cache_plugin::@a6e54a9991d6732a3c5c"
		},
		{
			"backtrace" : 285,
			"id" : "routertest_metadata_cache_cache_plugin::@f245b5691cb221bf9528"
		},
		{
			"backtrace" : 289,
			"id" : "routertest_metadata_cache_instance_attributes::@f245b5691cb221bf9528"
		},
		{
			"backtrace" : 293,
			"id" : "routertest_metadata_cache_plugin_config::@f245b5691cb221bf9528"
		},
		{
			"backtrace" : 295,
			"id" : "mock_server_rest_client::@09c51ce0bca0d324c59e"
		},
		{
			"backtrace" : 300,
			"id" : "routertest_mock_server_authentication::@87fa2ec71ed914dd62ef"
		},
		{
			"backtrace" : 304,
			"id" : "routertest_mysql_protocol_classic_protocol_binary::@67cfec21026691170647"
		},
		{
			"backtrace" : 307,
			"id" : "routertest_mysql_protocol_classic_protocol_frame::@67cfec21026691170647"
		},
		{
			"backtrace" : 310,
			"id" : "routertest_mysql_protocol_classic_protocol_message::@67cfec21026691170647"
		},
		{
			"backtrace" : 313,
			"id" : "routertest_mysql_protocol_classic_protocol_session_track::@67cfec21026691170647"
		},
		{
			"backtrace" : 316,
			"id" : "routertest_mysql_protocol_classic_protocol_wire::@67cfec21026691170647"
		},
		{
			"backtrace" : 319,
			"id" : "routertest_mysql_protocol_classic_protocol::@67cfec21026691170647"
		},
		{
			"backtrace" : 322,
			"id" : "routertest_mysql_protocol_microbench::@67cfec21026691170647"
		},
		{
			"backtrace" : 325,
			"id" : "router_openssl::@0ab6a84a83e0f53b073d"
		},
		{
			"backtrace" : 328,
			"id" : "mysqlrouter_plugin_info::@3fb745bf54d42dd38894"
		},
		{
			"backtrace" : 333,
			"id" : "routertest_mysqlrouter_plugin_info_plugin_info_app::@054024fbfcf60bb6dcc8"
		},
		{
			"backtrace" : 336,
			"id" : "router_protobuf::@f5d528676b76cb1b7295"
		},
		{
			"backtrace" : 339,
			"id" : "rest_api::@b0207d5adfce3a3bca92"
		},
		{
			"backtrace" : 342,
			"id" : "rest_connection_pool::@f0a0d34670d3164a7f95"
		},
		{
			"backtrace" : 345,
			"id" : "rest_metadata_cache::@d06300f3aee16bdc8c04"
		},
		{
			"backtrace" : 348,
			"id" : "rest_router::@00ce049dd56f4e1f180f"
		},
		{
			"backtrace" : 351,
			"id" : "rest_routing::@1363964c9ba473b4f5b1"
		},
		{
			"backtrace" : 355,
			"id" : "routertest_router_certificate_generator::@8bb2e5c9a46d2dc27447"
		},
		{
			"backtrace" : 358,
			"id" : "routertest_router_certificate_handler::@8bb2e5c9a46d2dc27447"
		},
		{
			"backtrace" : 361,
			"id" : "routertest_router_uri::@8bb2e5c9a46d2dc27447"
		},
		{
			"backtrace" : 364,
			"id" : "routertest_router_utils::@8bb2e5c9a46d2dc27447"
		},
		{
			"backtrace" : 367,
			"id" : "routertest_router_mysqlrouter_utils::@8bb2e5c9a46d2dc27447"
		},
		{
			"backtrace" : 370,
			"id" : "routertest_router_log_filter::@8bb2e5c9a46d2dc27447"
		},
		{
			"backtrace" : 373,
			"id" : "routertest_router_config_files::@8bb2e5c9a46d2dc27447"
		},
		{
			"backtrace" : 376,
			"id" : "routertest_router_mysql_session::@8bb2e5c9a46d2dc27447"
		},
		{
			"backtrace" : 379,
			"id" : "routertest_router_windows_service::@8bb2e5c9a46d2dc27447"
		},
		{
			"backtrace" : 382,
			"id" : "routertest_router_mysqlrouter_app::@8bb2e5c9a46d2dc27447"
		},
		{
			"backtrace" : 385,
			"id" : "routertest_router_keyring_frontend::@8bb2e5c9a46d2dc27447"
		},
		{
			"backtrace" : 388,
			"id" : "routertest_issues_bug22084430::@8bb2e5c9a46d2dc27447"
		},
		{
			"backtrace" : 391,
			"id" : "routertest_issues_bug24909259::@8bb2e5c9a46d2dc27447"
		},
		{
			"backtrace" : 394,
			"id" : "routertest_router_default_paths::@8bb2e5c9a46d2dc27447"
		},
		{
			"backtrace" : 397,
			"id" : "routing_plugin::@65ecc95f5e65f3e05ff0"
		},
		{
			"backtrace" : 402,
			"id" : "routertest_routing_block_clients::@ee74685db88a0185b2c8"
		},
		{
			"backtrace" : 406,
			"id" : "routertest_routing_connection_container::@ee74685db88a0185b2c8"
		},
		{
			"backtrace" : 410,
			"id" : "routertest_routing_first_available::@ee74685db88a0185b2c8"
		},
		{
			"backtrace" : 414,
			"id" : "routertest_routing_metadata_cache_group::@ee74685db88a0185b2c8"
		},
		{
			"backtrace" : 418,
			"id" : "routertest_routing_next_available::@ee74685db88a0185b2c8"
		},
		{
			"backtrace" : 422,
			"id" : "routertest_routing_round_robin::@ee74685db88a0185b2c8"
		},
		{
			"backtrace" : 426,
			"id" : "routertest_routing_routing::@ee74685db88a0185b2c8"
		},
		{
			"backtrace" : 430,
			"id" : "routertest_routing_setup_named_socket_service::@ee74685db88a0185b2c8"
		},
		{
			"backtrace" : 434,
			"id" : "routertest_routing_setup_tcp_service::@ee74685db88a0185b2c8"
		},
		{
			"backtrace" : 438,
			"id" : "routertest_routing_auth_digest::@ee74685db88a0185b2c8"
		},
		{
			"backtrace" : 442,
			"id" : "routertest_routing_classic_quit_sender::@ee74685db88a0185b2c8"
		},
		{
			"backtrace" : 446,
			"id" : "routertest_routing_classic_reset_connection_sender::@ee74685db88a0185b2c8"
		},
		{
			"backtrace" : 450,
			"id" : "routertest_routing_plugin::@ee74685db88a0185b2c8"
		},
		{
			"backtrace" : 453,
			"id" : "routertest_routing_classic_protocol_splicer::@ee74685db88a0185b2c8"
		},
		{
			"backtrace" : 458,
			"id" : "routertest_integration_routing_direct::@f6e6c9b43fe052e4f689"
		},
		{
			"backtrace" : 462,
			"id" : "routertest_integration_routing_reuse::@f6e6c9b43fe052e4f689"
		},
		{
			"backtrace" : 466,
			"id" : "routertest_integration_routing_sharing::@f6e6c9b43fe052e4f689"
		},
		{
			"backtrace" : 470,
			"id" : "routertest_integration_routing_sharing_constrained_pools::@f6e6c9b43fe052e4f689"
		},
		{
			"backtrace" : 474,
			"id" : "routertest_integration_routing_sharing_restart::@f6e6c9b43fe052e4f689"
		}
	],
	"id" : "mysqlrouter_all::@ae48964325684403f423",
	"name" : "mysqlrouter_all",
	"paths" : 
	{
		"build" : "router",
		"source" : "router"
	},
	"sources" : [],
	"type" : "UTILITY"
}
